<Catalog>
    <Marca>
        <NombreMarca>Chevrolet</NombreMarca>
        <ModeloAuto>Onix</ModeloAuto>
        <ModeloAuto>Prisma</ModeloAuto>
        <ModeloAuto>Cobalt</ModeloAuto>
        <ModeloAuto>Cruze</ModeloAuto>
        <ModeloAuto>Captiva</ModeloAuto>
    </Marca>
    <Marca>
        <NombreMarca>Hyundai</NombreMarca>
        <ModeloAuto>Accent</ModeloAuto>
        <ModeloAuto>Elantra</ModeloAuto>
        <ModeloAuto>Eon</ModeloAuto>
        <ModeloAuto>Santa Fe</ModeloAuto>
        <ModeloAuto>Tucson</ModeloAuto>
    </Marca>
    <Marca>
        <NombreMarca>Kia</NombreMarca>
        <ModeloAuto>Carens</ModeloAuto>
        <ModeloAuto>Rio</ModeloAuto>
        <ModeloAuto>Concord</ModeloAuto>
        <ModeloAuto>Carnival</ModeloAuto>
        <ModeloAuto>Cerato</ModeloAuto>
    </Marca>
    <Marca>
        <NombreMarca>Nissan</NombreMarca>
        <ModeloAuto>350Z</ModeloAuto>
        <ModeloAuto>Juke</ModeloAuto>
        <ModeloAuto>Sentra</ModeloAuto>
        <ModeloAuto>Sentra</ModeloAuto>
        <ModeloAuto>Qashqai</ModeloAuto>
    </Marca>
    <Marca>
        <NombreMarca>Toyota</NombreMarca>
        <ModeloAuto>Celica</ModeloAuto>
        <ModeloAuto>Corolla</ModeloAuto>
        <ModeloAuto>Prius</ModeloAuto>
        <ModeloAuto>Yaris</ModeloAuto>
        <ModeloAuto>Supra</ModeloAuto>
    </Marca>
    <Marca>
        <NombreMarca>Suzuki</NombreMarca>
        <ModeloAuto>Alto</ModeloAuto>
        <ModeloAuto>Grand Vitara</ModeloAuto>
        <ModeloAuto>Ignis</ModeloAuto>
        <ModeloAuto>Baleno</ModeloAuto>
        <ModeloAuto>Maruti</ModeloAuto>
    </Marca>
    <Marca>
        <NombreMarca>Ford</NombreMarca>
        <ModeloAuto>Courier</ModeloAuto>
        <ModeloAuto>Fiesta</ModeloAuto>
        <ModeloAuto>Focus</ModeloAuto>
        <ModeloAuto>F-150</ModeloAuto>
        <ModeloAuto>Mustang</ModeloAuto>
    </Marca>
    <Marca>
        <NombreMarca>Peugeot</NombreMarca>
        <ModeloAuto>307</ModeloAuto>
        <ModeloAuto>Bipper</ModeloAuto>
        <ModeloAuto>206</ModeloAuto>
        <ModeloAuto>Boxer</ModeloAuto>
        <ModeloAuto>Expert</ModeloAuto>
    </Marca>
    <Marca>
        <NombreMarca>Mazda</NombreMarca>
        <ModeloAuto>Furai</ModeloAuto>
        <ModeloAuto>Navajo</ModeloAuto>
        <ModeloAuto>RX-8</ModeloAuto>
        <ModeloAuto>Tribute</ModeloAuto>
        <ModeloAuto>Xedos</ModeloAuto>
    </Marca>
    <Marca>
        <NombreMarca>Mitsubishi</NombreMarca>
        <ModeloAuto>Carisma</ModeloAuto>
        <ModeloAuto>Challenger</ModeloAuto>
        <ModeloAuto>Galant</ModeloAuto>
        <ModeloAuto>Lancer</ModeloAuto>
        <ModeloAuto>Outlander</ModeloAuto>
    </Marca>
</Catalog>